lyricsfinder/__init__.py
lyricsfinder/lyricsfinder3.py
lyricsfinder3-0.1.dist-info/METADATA
lyricsfinder3-0.1.dist-info/WHEEL
lyricsfinder3-0.1.dist-info/top_level.txt
lyricsfinder3-0.1.dist-info/RECORD
