Metadata-Version: 2.1
Name: lyricsfinder3
Version: 0.1
Summary: A simple library to find song lyrics.
Home-page: https://github.com/yourusername/lyrics_finder
Author: Ramya
Author-email: ramyacp97@gmail.com
Classifier: Programming Language :: Python :: 3
Classifier: License :: OSI Approved :: MIT License
Classifier: Operating System :: OS Independent
Requires-Python: >=3.6
Requires-Dist: requests
Requires-Dist: beautifulsoup4
